price_alert/__init__.py
price_alert/price_monitoring.py
price_alert/utils/__init__.py
price_alert/utils/alert.py
price_alert/utils/common_tools.py
price_alert_rhsm-0.0.4.dist-info/LICENSE
price_alert_rhsm-0.0.4.dist-info/METADATA
price_alert_rhsm-0.0.4.dist-info/WHEEL
price_alert_rhsm-0.0.4.dist-info/top_level.txt
price_alert_rhsm-0.0.4.dist-info/RECORD
