Metadata-Version: 2.1
Name: price-alert-rhsm
Version: 0.0.4
Summary: Script to monitoring price.
Home-page: https://github.com/rafael-hsm/price_alert
Author: Rafael Meireles
Author-email: rafameireles2011@gmail.com
License: UNKNOWN
Platform: UNKNOWN
Requires-Python: >=3.8
License-File: LICENSE
Requires-Dist: yfinance
Requires-Dist: schedule
